MANIFEST.in
README.rst
README.txt
SDLCSService.py
requirements.txt
setup.py
SDLCSService/__init__.py
SDLCSService.egg-info/PKG-INFO
SDLCSService.egg-info/SOURCES.txt
SDLCSService.egg-info/dependency_links.txt
SDLCSService.egg-info/requires.txt
SDLCSService.egg-info/top_level.txt
SDLCSService/Conf/__init__.py
SDLCSService/Core/Config.py
SDLCSService/Core/Connection.py
SDLCSService/Core/DatetimePlus.py
SDLCSService/Core/FileManager.py
SDLCSService/Core/FuncHelper.py
SDLCSService/Core/HttpTesterBase.py
SDLCSService/Core/InterfaceBase.py
SDLCSService/Core/Logger.py
SDLCSService/Core/Router.py
SDLCSService/Core/ServiceBase.py
SDLCSService/Core/ServiceManager.py
SDLCSService/Core/__init__.py